fastapikit/__init__.py
fastapikit/database.py
fastapikit/repository.py
fastapikit/service.py
fastapikitx-0.1.1.dist-info/METADATA
fastapikitx-0.1.1.dist-info/WHEEL
fastapikitx-0.1.1.dist-info/licenses/LICENSE
fastapikitx-0.1.1.dist-info/RECORD
