Metadata-Version: 2.4
Name: fastapikitx
Version: 0.1.1
Summary: A lightweight FastAPI toolkit for structuring apps with services, repositories, and utils.
Project-URL: Homepage, https://github.com/nokokiii/fastapikit
Project-URL: Repository, https://github.com/nokokiii/fastapikit
Project-URL: Bug Tracker, https://github.com/nokokiii/fastapikit/issues
Author-email: nokokiii <kubanokoki@gmail.com>
License: MIT
License-File: LICENSE
Requires-Python: >=3.8
Requires-Dist: fastapi>=0.110.0
Requires-Dist: pydantic>=2.0
Requires-Dist: typing-extensions>=4.0
